{
  "miniprogramRoot": "dist/",
  "projectname": "wechat-miniapp",
  "description": "微信小程序",
  "appid": "wx38b3b6bbdb9b9ec0",
  "setting": {
    "urlCheck": true,
    "es6": true,
    "enhance": true,
    "compileHotReLoad": false,
    "postcss": false,
    "minified": true,
    "compileWorklet": false,
    "uglifyFileName": false,
    "uploadWithSourceMap": true,
    "packNpmManually": false,
    "packNpmRelationList": [],
    "minifyWXSS": true,
    "minifyWXML": true,
    "localPlugins": false,
    "disableUseStrict": false,
    "useCompilerPlugins": false,
    "condition": true,
    "swc": false,
    "disableSWC": true,
    "babelSetting": {
      "ignore": [],
      "disablePlugins": [],
      "outputPath": ""
    }
  },
  "compileType": "miniprogram",
  "simulatorPluginLibVersion": {},
  "packOptions": {
    "ignore": [],
    "include": []
  },
  "editorSetting": {},
  "libVersion": "3.9.0"
}